camalis_lib/__init__.py
camalis_lib/core.py
camalis_lib/dataset.py
camalis_lib/element.py
camalis_lib/event.py
camalis_lib/exceptions.py
camalis_lib/main.py
camalis_lib/model.py
camalis_lib/utils.py
camalis_lib/variable.py
camalis_lib-2025.1.15.dist-info/METADATA
camalis_lib-2025.1.15.dist-info/WHEEL
camalis_lib-2025.1.15.dist-info/RECORD
